evo/LICENSE
evo/__init__.py
evo/common_ape_rpe.py
evo/entry_points.py
evo/ipython_config.py
evo/main_ape.py
evo/main_ape_parser.py
evo/main_config.py
evo/main_evo.py
evo/main_ipython.py
evo/main_res.py
evo/main_res_parser.py
evo/main_rpe.py
evo/main_rpe_parser.py
evo/main_traj.py
evo/main_traj_parser.py
evo/core/__init__.py
evo/core/filters.py
evo/core/geometry.py
evo/core/lie_algebra.py
evo/core/metrics.py
evo/core/result.py
evo/core/sync.py
evo/core/trajectory.py
evo/core/transformations.py
evo/core/units.py
evo/tools/__init__.py
evo/tools/_typing.py
evo/tools/contextily_helper.py
evo/tools/file_interface.py
evo/tools/log.py
evo/tools/pandas_bridge.py
evo/tools/plot.py
evo/tools/rerun_bridge.py
evo/tools/settings.py
evo/tools/settings_template.py
evo/tools/tf_cache.py
evo/tools/tf_id.py
evo/tools/user.py
evo-1.34.0.dist-info/METADATA
evo-1.34.0.dist-info/WHEEL
evo-1.34.0.dist-info/entry_points.txt
evo-1.34.0.dist-info/licenses/LICENSE
evo-1.34.0.dist-info/RECORD
