Metadata-Version: 2.4
Name: evo
Version: 1.34.0
Summary: Python package for the evaluation of odometry and SLAM
Project-URL: Homepage, https://github.com/MichaelGrupp/evo
Project-URL: Wiki, https://github.com/MichaelGrupp/evo/wiki
Project-URL: Bugtracker, https://github.com/MichaelGrupp/evo/issues
Author-email: Michael Grupp <michael.grupp@tum.de>
License: GNU General Public License v3 (GPLv3)
License-File: LICENSE
Keywords: SLAM,evaluation,laser,metric,odometry,robotics,trajectory,vision,visual
Classifier: License :: OSI Approved :: GNU General Public License v3 (GPLv3)
Classifier: Programming Language :: Python
Classifier: Programming Language :: Python :: 3
Classifier: Programming Language :: Python :: 3.10
Classifier: Programming Language :: Python :: 3.11
Classifier: Programming Language :: Python :: 3.12
Classifier: Programming Language :: Python :: 3.13
Classifier: Programming Language :: Python :: 3.14
Classifier: Programming Language :: Python :: Implementation :: CPython
Classifier: Topic :: Scientific/Engineering
Requires-Python: >=3.10
Requires-Dist: argcomplete
Requires-Dist: colorama>=0.3
Requires-Dist: matplotlib>=3.6.0
Requires-Dist: natsort
Requires-Dist: numexpr>=2.7.3
Requires-Dist: numpy>=1.18.5
Requires-Dist: packaging
Requires-Dist: pandas
Requires-Dist: pillow
Requires-Dist: pygments
Requires-Dist: pyyaml
Requires-Dist: rosbags>=0.11.0
Requires-Dist: scipy>=1.2
Requires-Dist: seaborn>=0.9
Provides-Extra: geo
Requires-Dist: contextily; extra == 'geo'
Provides-Extra: gui
Requires-Dist: pyqt6; extra == 'gui'
Provides-Extra: rerun
Requires-Dist: rerun-sdk>=0.24.0; extra == 'rerun'
